pipeplot.py
pipeplot-0.3.3.dist-info/LICENSE
pipeplot-0.3.3.dist-info/METADATA
pipeplot-0.3.3.dist-info/WHEEL
pipeplot-0.3.3.dist-info/entry_points.txt
pipeplot-0.3.3.dist-info/top_level.txt
pipeplot-0.3.3.dist-info/RECORD
